README.md
setup.py
metos3d.egg-info/PKG-INFO
metos3d.egg-info/SOURCES.txt
metos3d.egg-info/dependency_links.txt
metos3d.egg-info/entry_points.txt
metos3d.egg-info/not-zip-safe
metos3d.egg-info/requires.txt
metos3d.egg-info/top_level.txt
metos3dpy/__init__.py
metos3dpy/metos3d.py
metos3dpy/version.py