Metadata-Version: 2.1
Name: metos3d
Version: 1.0.4
Summary: Marine Ecosystem Toolkit for Optimization and Simulation in 3-D
Home-page: https://github.com/metos3d
Author: Jaroslaw Piwonski (CAU)
Author-email: jpi@informatik.uni-kiel.de
License: GPL-3.0
Platform: UNKNOWN
